{
  "project_info": {
    "project_number": "812381404470",
    "project_id": "planeazy-7681f",
    "storage_bucket": "planeazy-7681f.firebasestorage.app"
  },
  "client": [
    {
      "client_info": {
        "mobilesdk_app_id": "1:812381404470:android:f7f8795e0e0eb42842c797",
        "android_client_info": {
          "package_name": "com.nesh.planeazy"
        }
      },
      "oauth_client": [],
      "api_key": [
        {
          "current_key": "AIzaSyBhg8vh0_4n0WBjXZhLIQYCxr5GRRsB7Rc"
        }
      ],
      "services": {
        "appinvite_service": {
          "other_platform_oauth_client": []
        }
      }
    }
  ],
  "configuration_version": "1"
}